superviolin/__init__.py
superviolin/plot.py
superviolin/plot_cli.py
superviolin/test_plot.py
superviolin/res/__init__.py
superviolin/res/args.txt
superviolin/res/demo_args.txt
superviolin/res/demo_data.csv
superviolin/res/test.pkl
superviolin-1.0.6.dist-info/LICENSE
superviolin-1.0.6.dist-info/METADATA
superviolin-1.0.6.dist-info/WHEEL
superviolin-1.0.6.dist-info/entry_points.txt
superviolin-1.0.6.dist-info/top_level.txt
superviolin-1.0.6.dist-info/RECORD
