Metadata-Version: 2.1
Name: superviolin
Version: 1.0.6
Summary: Python CLI to make Violin SuperPlots
Home-page: UNKNOWN
Author: Martin Kenny
Author-email: sideproject1892@gmail.com
Maintainer: Martin Kenny
Maintainer-email: sideproject1892@gmail.com
License: UNKNOWN
Platform: UNKNOWN
Classifier: Programming Language :: Python :: 3.6
Classifier: Programming Language :: Python :: 3.7
Classifier: Programming Language :: Python :: 3.8
Classifier: Programming Language :: Python :: 3.9
Classifier: License :: OSI Approved :: MIT License
Classifier: Operating System :: OS Independent
Requires-Python: >=3.6.2
License-File: LICENSE
Requires-Dist: appdirs
Requires-Dist: click
Requires-Dist: matplotlib
Requires-Dist: numpy
Requires-Dist: pandas
Requires-Dist: scipy
Requires-Dist: xlrd
Requires-Dist: openpyxl
Requires-Dist: scikit-posthocs
